{"features":[{"feature_idx":0,"name":"Plant","type":{"dtype":"string","_type":"Value"}},{"feature_idx":1,"name":"Light","type":{"dtype":"string","_type":"Value"}},{"feature_idx":2,"name":"Watering","type":{"dtype":"string","_type":"Value"}},{"feature_idx":3,"name":"Humidity","type":{"dtype":"string","_type":"Value"}},{"feature_idx":4,"name":"Temperature","type":{"dtype":"string","_type":"Value"}},{"feature_idx":5,"name":"Fertilizer","type":{"dtype":"string","_type":"Value"}},{"feature_idx":6,"name":"Pruning","type":{"dtype":"string","_type":"Value"}},{"feature_idx":7,"name":"Propagation","type":{"dtype":"string","_type":"Value"}},{"feature_idx":8,"name":"Notes","type":{"dtype":"string","_type":"Value"}},{"feature_idx":9,"name":"Unnamed: 9","type":{"dtype":"string","_type":"Value"}}],"rows":[{"row_idx":0,"row":{"Plant":"Rosemary","Light":"\"Full sun\"","Watering":"\"Moderate\"","Humidity":"\"Well-drained\"","Temperature":"\"Balanced\"","Fertilizer":"\"Warm\"","Pruning":"\"Low\"","Propagation":"\"Regularly\"","Notes":"\"Cuttings\"","Unnamed: 9":null},"truncated_cells":[]},{"row_idx":1,"row":{"Plant":"Lavender","Light":"\"Full sun\"","Watering":"\"Moderate\"","Humidity":"\"Well-drained\"","Temperature":"\"Low\"","Fertilizer":"\"Warm\"","Pruning":"\"Low\"","Propagation":"\"After flowering\"","Notes":"\"Cuttings\"","Unnamed: 9":null},"truncated_cells":[]},{"row_idx":2,"row":{"Plant":"Sage","Light":"\"Full sun\"","Watering":"\"Moderate\"","Humidity":"\"Well-drained\"","Temperature":"\"Low\"","Fertilizer":"\"Warm\"","Pruning":"\"Low\"","Propagation":"\"After flowering\"","Notes":"\"Cuttings\"","Unnamed: 9":null},"truncated_cells":[]},{"row_idx":3,"row":{"Plant":"Thyme","Light":"\"Full sun\"","Watering":"\"Moderate\"","Humidity":"\"Well-drained\"","Temperature":"\"Low\"","Fertilizer":"\"Warm\"","Pruning":"\"Low\"","Propagation":"\"After flowering\"","Notes":"\"Cuttings\"","Unnamed: 9":null},"truncated_cells":[]},{"row_idx":4,"row":{"Plant":"Oregano","Light":"\"Full sun\"","Watering":"\"Moderate\"","Humidity":"\"Well-drained\"","Temperature":"\"Low\"","Fertilizer":"\"Warm\"","Pruning":"\"Low\"","Propagation":"\"After flowering\"","Notes":"\"Cuttings\"","Unnamed: 9":null},"truncated_cells":[]},{"row_idx":5,"row":{"Plant":"Basil","Light":"\"Full sun\"","Watering":"\"Regular\"","Humidity":"\"Well-drained\"","Temperature":"\"Balanced\"","Fertilizer":"\"Warm\"","Pruning":"\"Moderate\"","Propagation":"\"Pinch back\"","Notes":"\"Seeds\"","Unnamed: 9":null},"truncated_cells":[]},{"row_idx":6,"row":{"Plant":"Mint","Light":"\"Partial shade\"","Watering":"\"Regular\"","Humidity":"\"Well-drained\"","Temperature":"\"Balanced\"","Fertilizer":"\"Cool\"","Pruning":"\"Moderate\"","Propagation":"\"Pinch back\"","Notes":"\"Division\"","Unnamed: 9":null},"truncated_cells":[]},{"row_idx":7,"row":{"Plant":"Parsley","Light":"\"Full sun\"","Watering":"\"Regular\"","Humidity":"\"Well-drained\"","Temperature":"\"Balanced\"","Fertilizer":"\"Cool\"","Pruning":"\"Moderate\"","Propagation":"\"Pinch back\"","Notes":"\"Seeds\"","Unnamed: 9":null},"truncated_cells":[]},{"row_idx":8,"row":{"Plant":"Dill","Light":"\"Full sun\"","Watering":"\"Regular\"","Humidity":"\"Well-drained\"","Temperature":"\"Balanced\"","Fertilizer":"\"Cool\"","Pruning":"\"Moderate\"","Propagation":"\"Pinch back\"","Notes":"\"Seeds\"","Unnamed: 9":null},"truncated_cells":[]},{"row_idx":9,"row":{"Plant":"Chives","Light":"\"Full sun\"","Watering":"\"Moderate\"","Humidity":"\"Well-drained\"","Temperature":"\"Balanced\"","Fertilizer":"\"Cool\"","Pruning":"\"Moderate\"","Propagation":"\"Regularly\"","Notes":"\"Division\"","Unnamed: 9":null},"truncated_cells":[]},{"row_idx":10,"row":{"Plant":"Peppers","Light":"\"Full sun\"","Watering":"\"Moderate\"","Humidity":"\"Well-drained\"","Temperature":"\"Balanced\"","Fertilizer":"\"Warm\"","Pruning":"\"Moderate\"","Propagation":"\"Regularly\"","Notes":"\"Seeds\"","Unnamed: 9":null},"truncated_cells":[]},{"row_idx":11,"row":{"Plant":"Tomatoes","Light":"\"Full sun\"","Watering":"\"Regular\"","Humidity":"\"Well-drained\"","Temperature":"\"Balanced\"","Fertilizer":"\"Warm\"","Pruning":"\"Moderate\"","Propagation":"\"Pinch back\"","Notes":"\"Seeds\"","Unnamed: 9":null},"truncated_cells":[]},{"row_idx":12,"row":{"Plant":"Cucumbers","Light":"\"Full sun\"","Watering":"\"Regular\"","Humidity":"\"Well-drained\"","Temperature":"\"Balanced\"","Fertilizer":"\"Warm\"","Pruning":"\"Moderate\"","Propagation":"\"Pinch back\"","Notes":"\"Seeds\"","Unnamed: 9":null},"truncated_cells":[]},{"row_idx":13,"row":{"Plant":"Zucchini","Light":"\"Full sun\"","Watering":"\"Regular\"","Humidity":"\"Well-drained\"","Temperature":"\"Balanced\"","Fertilizer":"\"Warm\"","Pruning":"\"Moderate\"","Propagation":"\"Pinch back\"","Notes":"\"Seeds\"","Unnamed: 9":null},"truncated_cells":[]},{"row_idx":14,"row":{"Plant":"Squash","Light":"\"Full sun\"","Watering":"\"Regular\"","Humidity":"\"Well-drained\"","Temperature":"\"Balanced\"","Fertilizer":"\"Warm\"","Pruning":"\"Moderate\"","Propagation":"\"Pinch back\"","Notes":"\"Seeds\"","Unnamed: 9":null},"truncated_cells":[]},{"row_idx":15,"row":{"Plant":"Beans","Light":"\"Full sun\"","Watering":"\"Regular\"","Humidity":"\"Well-drained\"","Temperature":"\"Balanced\"","Fertilizer":"\"Warm\"","Pruning":"\"Moderate\"","Propagation":"\"Pinch back\"","Notes":"\"Seeds\"","Unnamed: 9":null},"truncated_cells":[]},{"row_idx":16,"row":{"Plant":"Peas","Light":"\"Full sun\"","Watering":"\"Regular\"","Humidity":"\"Well-drained\"","Temperature":"\"Balanced\"","Fertilizer":"\"Cool\"","Pruning":"\"Moderate\"","Propagation":"\"Pinch back\"","Notes":"\"Seeds\"","Unnamed: 9":null},"truncated_cells":[]},{"row_idx":17,"row":{"Plant":"Strawberries","Light":"\"Full sun\"","Watering":"\"Regular\"","Humidity":"\"Well-drained\"","Temperature":"\"Balanced\"","Fertilizer":"\"Cool\"","Pruning":"\"Moderate\"","Propagation":"\"Pinch back\"","Notes":"\"Runners\"","Unnamed: 9":null},"truncated_cells":[]},{"row_idx":18,"row":{"Plant":"Blueberries","Light":"\"Partial shade\"","Watering":"\"Regular\"","Humidity":"\"Acidic\"","Temperature":"\"Balanced\"","Fertilizer":"\"Cool\"","Pruning":"\"Moderate\"","Propagation":"\"After flowering\"","Notes":"\"Cuttings\"","Unnamed: 9":null},"truncated_cells":[]},{"row_idx":19,"row":{"Plant":"Raspberries","Light":"\"Full sun\"","Watering":"\"Regular\"","Humidity":"\"Well-drained\"","Temperature":"\"Balanced\"","Fertilizer":"\"Cool\"","Pruning":"\"Moderate\"","Propagation":"\"After flowering\"","Notes":"\"Division\"","Unnamed: 9":null},"truncated_cells":[]},{"row_idx":20,"row":{"Plant":"Blackberries","Light":"\"Full sun\"","Watering":"\"Regular\"","Humidity":"\"Well-drained\"","Temperature":"\"Balanced\"","Fertilizer":"\"Cool\"","Pruning":"\"Moderate\"","Propagation":"\"After flowering\"","Notes":"\"Division\"","Unnamed: 9":null},"truncated_cells":[]},{"row_idx":21,"row":{"Plant":"Apples","Light":"\"Full sun\"","Watering":"\"Regular\"","Humidity":"\"Well-drained\"","Temperature":"\"Balanced\"","Fertilizer":"\"Cool\"","Pruning":"\"Moderate\"","Propagation":"\"After flowering\"","Notes":"\"Grafting\"","Unnamed: 9":null},"truncated_cells":[]},{"row_idx":22,"row":{"Plant":"Pears","Light":"\"Full sun\"","Watering":"\"Regular\"","Humidity":"\"Well-drained\"","Temperature":"\"Balanced\"","Fertilizer":"\"Cool\"","Pruning":"\"Moderate\"","Propagation":"\"After flowering\"","Notes":"\"Grafting\"","Unnamed: 9":null},"truncated_cells":[]},{"row_idx":23,"row":{"Plant":"Cherries","Light":"\"Full sun\"","Watering":"\"Regular\"","Humidity":"\"Well-drained\"","Temperature":"\"Balanced\"","Fertilizer":"\"Cool\"","Pruning":"\"Moderate\"","Propagation":"\"After flowering\"","Notes":"\"Grafting\"","Unnamed: 9":null},"truncated_cells":[]},{"row_idx":24,"row":{"Plant":"Peaches","Light":"\"Full sun\"","Watering":"\"Regular\"","Humidity":"\"Well-drained\"","Temperature":"\"Balanced\"","Fertilizer":"\"Warm\"","Pruning":"\"Moderate\"","Propagation":"\"After flowering\"","Notes":"\"Grafting\"","Unnamed: 9":null},"truncated_cells":[]},{"row_idx":25,"row":{"Plant":"Nectarines","Light":"\"Full sun\"","Watering":"\"Regular\"","Humidity":"\"Well-drained\"","Temperature":"\"Balanced\"","Fertilizer":"\"Warm\"","Pruning":"\"Moderate\"","Propagation":"\"After flowering\"","Notes":"\"Grafting\"","Unnamed: 9":null},"truncated_cells":[]},{"row_idx":26,"row":{"Plant":"Plums","Light":"\"Full sun\"","Watering":"\"Regular\"","Humidity":"\"Well-drained\"","Temperature":"\"Balanced\"","Fertilizer":"\"Cool\"","Pruning":"\"Moderate\"","Propagation":"\"After flowering\"","Notes":"\"Grafting\"","Unnamed: 9":null},"truncated_cells":[]},{"row_idx":27,"row":{"Plant":"Apricots","Light":"\"Full sun\"","Watering":"\"Regular\"","Humidity":"\"Well-drained\"","Temperature":"\"Balanced\"","Fertilizer":"\"Warm\"","Pruning":"\"Moderate\"","Propagation":"\"After flowering\"","Notes":"\"Grafting\"","Unnamed: 9":null},"truncated_cells":[]},{"row_idx":28,"row":{"Plant":"Figs","Light":"\"Full sun\"","Watering":"\"Moderate\"","Humidity":"\"Well-drained\"","Temperature":"\"Balanced\"","Fertilizer":"\"Warm\"","Pruning":"\"Low\"","Propagation":"\"After fruiting\"","Notes":"\"Cuttings\"","Unnamed: 9":null},"truncated_cells":[]},{"row_idx":29,"row":{"Plant":"Grapes","Light":"\"Full sun\"","Watering":"\"Regular\"","Humidity":"\"Well-drained\"","Temperature":"\"Balanced\"","Fertilizer":"\"Warm\"","Pruning":"\"Moderate\"","Propagation":"\"After fruiting\"","Notes":"\"Cuttings\"","Unnamed: 9":null},"truncated_cells":[]},{"row_idx":30,"row":{"Plant":"Avocado","Light":"\"Partial shade\"","Watering":"\"Moderate\"","Humidity":"\"Well-drained\"","Temperature":"\"Balanced\"","Fertilizer":"\"Warm\"","Pruning":"\"Moderate\"","Propagation":"\"Pinch back\"","Notes":"\"Seeds\"","Unnamed: 9":null},"truncated_cells":[]},{"row_idx":31,"row":{"Plant":"Citrus","Light":"\"Full sun\"","Watering":"\"Regular\"","Humidity":"\"Well-drained\"","Temperature":"\"Balanced\"","Fertilizer":"\"Warm\"","Pruning":"\"Moderate\"","Propagation":"\"After fruiting\"","Notes":"\"Cuttings\"","Unnamed: 9":null},"truncated_cells":[]},{"row_idx":32,"row":{"Plant":"Mango","Light":"\"Full sun\"","Watering":"\"Moderate\"","Humidity":"\"Well-drained\"","Temperature":"\"Balanced\"","Fertilizer":"\"Warm\"","Pruning":"\"Moderate\"","Propagation":"\"After fruiting\"","Notes":"\"Seeds\"","Unnamed: 9":null},"truncated_cells":[]},{"row_idx":33,"row":{"Plant":"Pineapple","Light":"\"Full sun\"","Watering":"\"Moderate\"","Humidity":"\"Well-drained\"","Temperature":"\"Balanced\"","Fertilizer":"\"Warm\"","Pruning":"\"Moderate\"","Propagation":"\"After fruiting\"","Notes":"\"Crown\"","Unnamed: 9":null},"truncated_cells":[]},{"row_idx":34,"row":{"Plant":"Papaya","Light":"\"Full sun\"","Watering":"\"Regular\"","Humidity":"\"Well-drained\"","Temperature":"\"Balanced\"","Fertilizer":"\"Warm\"","Pruning":"\"Moderate\"","Propagation":"\"After fruiting\"","Notes":"\"Seeds\"","Unnamed: 9":null},"truncated_cells":[]},{"row_idx":35,"row":{"Plant":"Bananas","Light":"\"Full sun\"","Watering":"\"Regular\"","Humidity":"\"Well-drained\"","Temperature":"\"Balanced\"","Fertilizer":"\"Warm\"","Pruning":"\"Moderate\"","Propagation":"\"After fruiting\"","Notes":"\"Suckers\"","Unnamed: 9":null},"truncated_cells":[]},{"row_idx":36,"row":{"Plant":"Coffee","Light":"\"Partial shade\"","Watering":"\"Regular\"","Humidity":"\"Well-drained\"","Temperature":"\"Balanced\"","Fertilizer":"\"Warm\"","Pruning":"\"Moderate\"","Propagation":"\"After fruiting\"","Notes":"\"Seeds\"","Unnamed: 9":null},"truncated_cells":[]},{"row_idx":37,"row":{"Plant":"Tea","Light":"\"Partial shade\"","Watering":"\"Regular\"","Humidity":"\"Well-drained\"","Temperature":"\"Balanced\"","Fertilizer":"\"Warm\"","Pruning":"\"Moderate\"","Propagation":"\"After fruiting\"","Notes":"\"Cuttings\"","Unnamed: 9":null},"truncated_cells":[]},{"row_idx":38,"row":{"Plant":"Cactus","Light":"\"Full sun\"","Watering":"\"Moderate\"","Humidity":"\"Well-drained\"","Temperature":"\"Low\"","Fertilizer":"\"Warm\"","Pruning":"\"Low\"","Propagation":"\"After flowering\"","Notes":"\"Seeds\"","Unnamed: 9":null},"truncated_cells":[]},{"row_idx":39,"row":{"Plant":"Succulents","Light":"\"Full sun\"","Watering":"\"Moderate\"","Humidity":"\"Well-drained\"","Temperature":"\"Low\"","Fertilizer":"\"Warm\"","Pruning":"\"Low\"","Propagation":"\"After flowering\"","Notes":"\"Cuttings\"","Unnamed: 9":null},"truncated_cells":[]},{"row_idx":40,"row":{"Plant":"Orchids","Light":"\"Bright indirect light\"","Watering":"\"Moderate\"","Humidity":"\"Bark-based\"","Temperature":"\"Balanced\"","Fertilizer":"\"Warm\"","Pruning":"\"High\"","Propagation":"\"After flowering\"","Notes":"\"Division\"","Unnamed: 9":null},"truncated_cells":[]},{"row_idx":41,"row":{"Plant":"Ferns","Light":"\"Partial shade\"","Watering":"\"Regular\"","Humidity":"\"Moist\"","Temperature":"\"Balanced\"","Fertilizer":"\"Cool\"","Pruning":"\"High\"","Propagation":"\"After flowering\"","Notes":"\"Spores\"","Unnamed: 9":null},"truncated_cells":[]},{"row_idx":42,"row":{"Plant":"Houseplants","Light":"\"Bright indirect light\"","Watering":"\"Moderate\"","Humidity":"\"Potting mix\"","Temperature":"\"Balanced\"","Fertilizer":"\"Warm\"","Pruning":"\"Moderate\"","Propagation":"\"Regularly\"","Notes":"\"Cuttings\"","Unnamed: 9":null},"truncated_cells":[]},{"row_idx":43,"row":{"Plant":"Begonia","Light":"\"Bright indirect light\"","Watering":"\"Moderate\"","Humidity":"\"Potting mix\"","Temperature":"\"Balanced\"","Fertilizer":"\"Warm\"","Pruning":"\"Moderate\"","Propagation":"\"Pinch back\"","Notes":"\"Cuttings\"","Unnamed: 9":null},"truncated_cells":[]},{"row_idx":44,"row":{"Plant":"African Violet","Light":"\"Bright indirect light\"","Watering":"\"Moderate\"","Humidity":"\"Potting mix\"","Temperature":"\"Balanced\"","Fertilizer":"\"Warm\"","Pruning":"\"Moderate\"","Propagation":"\"Pinch back\"","Notes":"\"Leaf cuttings\"","Unnamed: 9":null},"truncated_cells":[]},{"row_idx":45,"row":{"Plant":"Pothos","Light":"\"Bright indirect light\"","Watering":"\"Moderate\"","Humidity":"\"Potting mix\"","Temperature":"\"Balanced\"","Fertilizer":"\"Warm\"","Pruning":"\"Moderate\"","Propagation":"\"Pinch back\"","Notes":"\"Cuttings\"","Unnamed: 9":null},"truncated_cells":[]},{"row_idx":46,"row":{"Plant":"Snake Plant","Light":"\"Bright indirect light\"","Watering":"\"Moderate\"","Humidity":"\"Potting mix\"","Temperature":"\"Balanced\"","Fertilizer":"\"Warm\"","Pruning":"\"Low\"","Propagation":"\"Pinch back\"","Notes":"\"Division\"","Unnamed: 9":null},"truncated_cells":[]},{"row_idx":47,"row":{"Plant":"Spider Plant","Light":"\"Bright indirect light\"","Watering":"\"Moderate\"","Humidity":"\"Potting mix\"","Temperature":"\"Balanced\"","Fertilizer":"\"Warm\"","Pruning":"\"Moderate\"","Propagation":"\"Pinch back\"","Notes":"\"Puppies\"","Unnamed: 9":null},"truncated_cells":[]},{"row_idx":48,"row":{"Plant":"ZZ Plant","Light":"\"Bright indirect light\"","Watering":"\"Moderate\"","Humidity":"\"Potting mix\"","Temperature":"\"Balanced\"","Fertilizer":"\"Warm\"","Pruning":"\"Low\"","Propagation":"\"Pinch back\"","Notes":"\"Division\"","Unnamed: 9":null},"truncated_cells":[]},{"row_idx":49,"row":{"Plant":"Peace Lily","Light":"\"Bright indirect light\"","Watering":"\"Moderate\"","Humidity":"\"Potting mix\"","Temperature":"\"Balanced\"","Fertilizer":"\"Warm\"","Pruning":"\"Moderate\"","Propagation":"\"Pinch back\"","Notes":"\"Division\"","Unnamed: 9":null},"truncated_cells":[]},{"row_idx":50,"row":{"Plant":"Monstera","Light":"\"Bright indirect light\"","Watering":"\"Moderate\"","Humidity":"\"Potting mix\"","Temperature":"\"Balanced\"","Fertilizer":"\"Warm\"","Pruning":"\"Moderate\"","Propagation":"\"Pinch back\"","Notes":"\"Cuttings\"","Unnamed: 9":null},"truncated_cells":[]},{"row_idx":51,"row":{"Plant":"Fiddle Leaf Fig","Light":"\"Bright indirect light\"","Watering":"\"Moderate\"","Humidity":"\"Potting mix\"","Temperature":"\"Balanced\"","Fertilizer":"\"Warm\"","Pruning":"\"Moderate\"","Propagation":"\"Pinch back\"","Notes":"\"Cuttings\"","Unnamed: 9":null},"truncated_cells":[]},{"row_idx":52,"row":{"Plant":"Calathea","Light":"\"Bright indirect light\"","Watering":"\"Moderate\"","Humidity":"\"Potting mix\"","Temperature":"\"Balanced\"","Fertilizer":"\"Warm\"","Pruning":"\"High\"","Propagation":"\"Pinch back\"","Notes":"\"Division\"","Unnamed: 9":null},"truncated_cells":[]},{"row_idx":53,"row":{"Plant":"Maranta","Light":"\"Bright indirect light\"","Watering":"\"Moderate\"","Humidity":"\"Potting mix\"","Temperature":"\"Balanced\"","Fertilizer":"\"Warm\"","Pruning":"\"High\"","Propagation":"\"Pinch back\"","Notes":"\"Division\"","Unnamed: 9":null},"truncated_cells":[]},{"row_idx":54,"row":{"Plant":"Philodendron","Light":"\"Bright indirect light\"","Watering":"\"Moderate\"","Humidity":"\"Potting mix\"","Temperature":"\"Balanced\"","Fertilizer":"\"Warm\"","Pruning":"\"Moderate\"","Propagation":"\"Pinch back\"","Notes":"\"Cuttings\"","Unnamed: 9":null},"truncated_cells":[]},{"row_idx":55,"row":{"Plant":"Dieffenbachia","Light":"\"Bright indirect light\"","Watering":"\"Moderate\"","Humidity":"\"Potting mix\"","Temperature":"\"Balanced\"","Fertilizer":"\"Warm\"","Pruning":"\"Moderate\"","Propagation":"\"Pinch back\"","Notes":"\"Cuttings\"","Unnamed: 9":null},"truncated_cells":[]},{"row_idx":56,"row":{"Plant":"Croton","Light":"\"Bright indirect light\"","Watering":"\"Moderate\"","Humidity":"\"Potting mix\"","Temperature":"\"Balanced\"","Fertilizer":"\"Warm\"","Pruning":"\"Moderate\"","Propagation":"\"Pinch back\"","Notes":"\"Cuttings\"","Unnamed: 9":null},"truncated_cells":[]},{"row_idx":57,"row":{"Plant":"Dracaena","Light":"\"Bright indirect light\"","Watering":"\"Moderate\"","Humidity":"\"Potting mix\"","Temperature":"\"Balanced\"","Fertilizer":"\"Warm\"","Pruning":"\"Moderate\"","Propagation":"\"Pinch back\"","Notes":"\"Cuttings\"","Unnamed: 9":null},"truncated_cells":[]},{"row_idx":58,"row":{"Plant":"Yucca","Light":"\"Bright indirect light\"","Watering":"\"Moderate\"","Humidity":"\"Well-drained\"","Temperature":"\"Balanced\"","Fertilizer":"\"Warm\"","Pruning":"\"Moderate\"","Propagation":"\"Pinch back\"","Notes":"\"Cuttings\"","Unnamed: 9":null},"truncated_cells":[]},{"row_idx":59,"row":{"Plant":"Alocasia","Light":"\"Bright indirect light\"","Watering":"\"Moderate\"","Humidity":"\"Potting mix\"","Temperature":"\"Balanced\"","Fertilizer":"\"Warm\"","Pruning":"\"High\"","Propagation":"\"Pinch back\"","Notes":"\"Division\"","Unnamed: 9":null},"truncated_cells":[]},{"row_idx":60,"row":{"Plant":"Anthurium","Light":"\"Bright indirect light\"","Watering":"\"Moderate\"","Humidity":"\"Potting mix\"","Temperature":"\"Balanced\"","Fertilizer":"\"Warm\"","Pruning":"\"High\"","Propagation":"\"Pinch back\"","Notes":"\"Division\"","Unnamed: 9":null},"truncated_cells":[]},{"row_idx":61,"row":{"Plant":"Bromeliad","Light":"\"Bright indirect light\"","Watering":"\"Moderate\"","Humidity":"\"Potting mix\"","Temperature":"\"Balanced\"","Fertilizer":"\"Warm\"","Pruning":"\"High\"","Propagation":"\"Pinch back\"","Notes":"\"Pups\"","Unnamed: 9":null},"truncated_cells":[]},{"row_idx":62,"row":{"Plant":"Hoya","Light":"\"Bright indirect light\"","Watering":"\"Moderate\"","Humidity":"\"Potting mix\"","Temperature":"\"Balanced\"","Fertilizer":"\"Warm\"","Pruning":"\"Moderate\"","Propagation":"\"Pinch back\"","Notes":"\"Cuttings\"","Unnamed: 9":null},"truncated_cells":[]},{"row_idx":63,"row":{"Plant":"Strawberry","Light":"Full sun to partial shade","Watering":"Regularly","Humidity":"Balanced fertilizer","Temperature":"Well-drained soil","Fertilizer":"60-85°F","Pruning":"Moderate","Propagation":"Remove runners and old leaves","Notes":"Early summer to fall","Unnamed: 9":null},"truncated_cells":[]},{"row_idx":64,"row":{"Plant":"Tomato","Light":"Full sun","Watering":"Regularly","Humidity":"Balanced fertilizer","Temperature":"Well-drained soil","Fertilizer":"65-85°F","Pruning":"Moderate","Propagation":"Prune suckers and leaves","Notes":"Late summer to fall","Unnamed: 9":null},"truncated_cells":[]},{"row_idx":65,"row":{"Plant":"Lettuce","Light":"Partial shade to full sun","Watering":"Regularly","Humidity":"Balanced fertilizer","Temperature":"Well-drained soil","Fertilizer":"55-75°F","Pruning":"Moderate","Propagation":"Harvest outer leaves as needed","Notes":"Spring to fall","Unnamed: 9":null},"truncated_cells":[]},{"row_idx":66,"row":{"Plant":"Basil","Light":"Full sun","Watering":"Regularly","Humidity":"Balanced fertilizer","Temperature":"Well-drained soil","Fertilizer":"65-85°F","Pruning":"Moderate","Propagation":"Pinch off flower buds","Notes":"Summer to fall","Unnamed: 9":null},"truncated_cells":[]},{"row_idx":67,"row":{"Plant":"Mint","Light":"Partial shade to full sun","Watering":"Regularly","Humidity":"Balanced fertilizer","Temperature":"Well-drained soil","Fertilizer":"55-75°F","Pruning":"Moderate","Propagation":"Cut stems back after flowering","Notes":"Summer to fall","Unnamed: 9":null},"truncated_cells":[]},{"row_idx":68,"row":{"Plant":"Cucumber","Light":"Full sun","Watering":"Regularly","Humidity":"Balanced fertilizer","Temperature":"Well-drained soil","Fertilizer":"65-85°F","Pruning":"Moderate","Propagation":"Pinch off side shoots and leaves","Notes":"Summer","Unnamed: 9":null},"truncated_cells":[]},{"row_idx":69,"row":{"Plant":"Bell pepper","Light":"Full sun","Watering":"Regularly","Humidity":"Balanced fertilizer","Temperature":"Well-drained soil","Fertilizer":"65-85°F","Pruning":"Moderate","Propagation":"Prune off suckers and leaves","Notes":"Summer to fall","Unnamed: 9":null},"truncated_cells":[]},{"row_idx":70,"row":{"Plant":"Green beans","Light":"Full sun","Watering":"Regularly","Humidity":"Balanced fertilizer","Temperature":"Well-drained soil","Fertilizer":"65-85°F","Pruning":"Moderate","Propagation":"Pinch off tips to encourage branching","Notes":"Summer to fall","Unnamed: 9":null},"truncated_cells":[]},{"row_idx":71,"row":{"Plant":"Zucchini","Light":"Full sun","Watering":"Regularly","Humidity":"Balanced fertilizer","Temperature":"Well-drained soil","Fertilizer":"65-85°F","Pruning":"Moderate","Propagation":"Pinch off side shoots and leaves","Notes":"Summer","Unnamed: 9":null},"truncated_cells":[]},{"row_idx":72,"row":{"Plant":"Spinach","Light":"Partial shade to full sun","Watering":"Regularly","Humidity":"Balanced fertilizer","Temperature":"Well-drained soil","Fertilizer":"55-75°F","Pruning":"Moderate","Propagation":"Harvest outer leaves as needed","Notes":"Spring to fall","Unnamed: 9":null},"truncated_cells":[]},{"row_idx":73,"row":{"Plant":"Kale","Light":"Full sun to partial shade","Watering":"Regularly","Humidity":"Balanced fertilizer","Temperature":"Well-drained soil","Fertilizer":"40-75°F","Pruning":"Moderate","Propagation":"Harvest outer leaves as needed","Notes":"Fall to spring","Unnamed: 9":null},"truncated_cells":[]},{"row_idx":74,"row":{"Plant":"Broccoli","Light":"Full sun","Watering":"Regularly","Humidity":"Balanced fertilizer","Temperature":"Well-drained soil","Fertilizer":"55-75°F","Pruning":"Moderate","Propagation":"Remove side shoots","Notes":"Spring to fall","Unnamed: 9":null},"truncated_cells":[]},{"row_idx":75,"row":{"Plant":"Cauliflower","Light":"Full sun","Watering":"Regularly","Humidity":"Balanced fertilizer","Temperature":"Well-drained soil","Fertilizer":"55-75°F","Pruning":"Moderate","Propagation":"Remove side shoots","Notes":"Spring to fall","Unnamed: 9":null},"truncated_cells":[]},{"row_idx":76,"row":{"Plant":"Radish","Light":"Full sun","Watering":"Regularly","Humidity":"Balanced fertilizer","Temperature":"Well-drained soil","Fertilizer":"40-75°F","Pruning":"Moderate","Propagation":"Harvest when radishes are firm","Notes":"Spring to fall","Unnamed: 9":null},"truncated_cells":[]},{"row_idx":77,"row":{"Plant":"Carrot","Light":"Full sun","Watering":"Regularly","Humidity":"Balanced fertilizer","Temperature":"Well-drained soil","Fertilizer":"40-75°F","Pruning":"Moderate","Propagation":"Thin seedlings","Notes":"Spring to fall","Unnamed: 9":null},"truncated_cells":[]},{"row_idx":78,"row":{"Plant":"Onion","Light":"Full sun","Watering":"Regularly","Humidity":"Balanced fertilizer","Temperature":"Well-drained soil","Fertilizer":"55-75°F","Pruning":"Moderate","Propagation":"Harvest bulbs when they are firm","Notes":"Summer to fall","Unnamed: 9":null},"truncated_cells":[]},{"row_idx":79,"row":{"Plant":"Garlic","Light":"Full sun","Watering":"Regularly","Humidity":"Balanced fertilizer","Temperature":"Well-drained soil","Fertilizer":"55-75°F","Pruning":"Moderate","Propagation":"Harvest bulbs when leaves turn brown","Notes":"Summer","Unnamed: 9":null},"truncated_cells":[]},{"row_idx":80,"row":{"Plant":"Potato","Light":"Full sun","Watering":"Regularly","Humidity":"Balanced fertilizer","Temperature":"Well-drained soil","Fertilizer":"65-85°F","Pruning":"Moderate","Propagation":"Hilling up soil around plants","Notes":"Summer","Unnamed: 9":null},"truncated_cells":[]},{"row_idx":81,"row":{"Plant":"Asparagus","Light":"Full sun","Watering":"Regularly","Humidity":"Balanced fertilizer","Temperature":"Well-drained soil","Fertilizer":"55-75°F","Pruning":"Moderate","Propagation":"Harvest spears in spring","Notes":"Spring","Unnamed: 9":null},"truncated_cells":[]},{"row_idx":82,"row":{"Plant":"Blueberry","Light":"Full sun to partial shade","Watering":"Regularly","Humidity":"Acidic fertilizer","Temperature":"Acidic soil","Fertilizer":"55-75°F","Pruning":"Moderate","Propagation":"Prune after fruiting","Notes":"Summer","Unnamed: 9":null},"truncated_cells":[]},{"row_idx":83,"row":{"Plant":"Raspberry","Light":"Full sun to partial shade","Watering":"Regularly","Humidity":"Balanced fertilizer","Temperature":"Well-drained soil","Fertilizer":"55-75°F","Pruning":"Moderate","Propagation":"Prune after fruiting","Notes":"Summer","Unnamed: 9":null},"truncated_cells":[]},{"row_idx":84,"row":{"Plant":"Blackberry","Light":"Full sun to partial shade","Watering":"Regularly","Humidity":"Balanced fertilizer","Temperature":"Well-drained soil","Fertilizer":"55-75°F","Pruning":"Moderate","Propagation":"Prune after fruiting","Notes":"Summer","Unnamed: 9":null},"truncated_cells":[]},{"row_idx":85,"row":{"Plant":"Grape","Light":"Full sun","Watering":"Regularly","Humidity":"Balanced fertilizer","Temperature":"Well-drained soil","Fertilizer":"55-75°F","Pruning":"Moderate","Propagation":"Prune in winter","Notes":"Fall","Unnamed: 9":null},"truncated_cells":[]},{"row_idx":86,"row":{"Plant":"Apple","Light":"Full sun","Watering":"Regularly","Humidity":"Balanced fertilizer","Temperature":"Well-drained soil","Fertilizer":"40-75°F","Pruning":"Moderate","Propagation":"Prune in winter","Notes":"Fall","Unnamed: 9":null},"truncated_cells":[]},{"row_idx":87,"row":{"Plant":"Pear","Light":"Full sun","Watering":"Regularly","Humidity":"Balanced fertilizer","Temperature":"Well-drained soil","Fertilizer":"40-75°F","Pruning":"Moderate","Propagation":"Prune in winter","Notes":"Fall","Unnamed: 9":null},"truncated_cells":[]},{"row_idx":88,"row":{"Plant":"Cherry","Light":"Full sun","Watering":"Regularly","Humidity":"Balanced fertilizer","Temperature":"Well-drained soil","Fertilizer":"40-75°F","Pruning":"Moderate","Propagation":"Prune in winter","Notes":"Fall","Unnamed: 9":null},"truncated_cells":[]},{"row_idx":89,"row":{"Plant":"Peach","Light":"Full sun","Watering":"Regularly","Humidity":"Balanced fertilizer","Temperature":"Well-drained soil","Fertilizer":"40-75°F","Pruning":"Moderate","Propagation":"Prune in winter","Notes":"Fall","Unnamed: 9":null},"truncated_cells":[]},{"row_idx":90,"row":{"Plant":"Plum","Light":"Full sun","Watering":"Regularly","Humidity":"Balanced fertilizer","Temperature":"Well-drained soil","Fertilizer":"40-75°F","Pruning":"Moderate","Propagation":"Prune in winter","Notes":"Fall","Unnamed: 9":null},"truncated_cells":[]},{"row_idx":91,"row":{"Plant":"Avocado","Light":"Full sun","Watering":"Regularly","Humidity":"Balanced fertilizer","Temperature":"Well-drained soil","Fertilizer":"65-85°F","Pruning":"Moderate","Propagation":"Prune after fruiting","Notes":"Fall","Unnamed: 9":null},"truncated_cells":[]},{"row_idx":92,"row":{"Plant":"Mango","Light":"Full sun","Watering":"Regularly","Humidity":"Balanced fertilizer","Temperature":"Well-drained soil","Fertilizer":"75-90°F","Pruning":"High","Propagation":"Prune after fruiting","Notes":"Summer","Unnamed: 9":null},"truncated_cells":[]},{"row_idx":93,"row":{"Plant":"Pineapple","Light":"Full sun","Watering":"Regularly","Humidity":"Balanced fertilizer","Temperature":"Well-drained soil","Fertilizer":"75-90°F","Pruning":"High","Propagation":"Prune after fruiting","Notes":"Summer","Unnamed: 9":null},"truncated_cells":[]},{"row_idx":94,"row":{"Plant":"Papaya","Light":"Full sun","Watering":"Regularly","Humidity":"Balanced fertilizer","Temperature":"Well-drained soil","Fertilizer":"75-90°F","Pruning":"High","Propagation":"Prune after fruiting","Notes":"Summer","Unnamed: 9":null},"truncated_cells":[]},{"row_idx":95,"row":{"Plant":"Lemon","Light":"Full sun","Watering":"Regularly","Humidity":"Balanced fertilizer","Temperature":"Well-drained soil","Fertilizer":"65-85°F","Pruning":"Moderate","Propagation":"Prune in winter","Notes":"Winter","Unnamed: 9":null},"truncated_cells":[]},{"row_idx":96,"row":{"Plant":"Orange","Light":"Full sun","Watering":"Regularly","Humidity":"Balanced fertilizer","Temperature":"Well-drained soil","Fertilizer":"65-85°F","Pruning":"Moderate","Propagation":"Prune in winter","Notes":"Winter","Unnamed: 9":null},"truncated_cells":[]},{"row_idx":97,"row":{"Plant":"Lime","Light":"Full sun","Watering":"Regularly","Humidity":"Balanced fertilizer","Temperature":"Well-drained soil","Fertilizer":"65-85°F","Pruning":"Moderate","Propagation":"Prune in winter","Notes":"Winter","Unnamed: 9":null},"truncated_cells":[]},{"row_idx":98,"row":{"Plant":"Grapefruit","Light":"Full sun","Watering":"Regularly","Humidity":"Balanced fertilizer","Temperature":"Well-drained soil","Fertilizer":"65-85°F","Pruning":"Moderate","Propagation":"Prune in winter","Notes":"Winter","Unnamed: 9":null},"truncated_cells":[]},{"row_idx":99,"row":{"Plant":"Fig","Light":"Full sun","Watering":"Regularly","Humidity":"Balanced fertilizer","Temperature":"Well-drained soil","Fertilizer":"65-85°F","Pruning":"Moderate","Propagation":"Prune after fruiting","Notes":"Fall","Unnamed: 9":null},"truncated_cells":[]}],"num_rows_total":3648,"num_rows_per_page":100,"partial":false}